{
  "favorites": [],
  "lookup_history": [
    "item:minecraft:smithing_table",
    "item:create:polished_rose_quartz",
    "item:sereneseasons:calendar",
    "item:backpacked:backpack",
    "item:paraglider:paraglider",
    "item:minecraft:spyglass",
    "item:endermanoverhaul:corrupted_shield{Damage:0}",
    "item:create:schematicannon",
    "item:trials:crafter",
    {
      "type": "item",
      "id": "farmersdelight:rope",
      "amount": 4
    },
    "item:farmersdelight:safety_net",
    "item:create:schematic_table",
    "item:create:schedule",
    "item:create:empty_schematic",
    "item:create:schematic_and_quill",
    "item:alexsmobs:kangaroo_hide",
    "item:minecraft:rabbit_hide",
    "item:quark:crafter"
  ],
  "craft_history": [],
  "recipe_defaults": {
    "added": [],
    "tags": {},
    "resolutions": {},
    "disabled": []
  },
  "hidden_stacks": [
    "item:farmersdelight:safety_net",
    "item:farmersdelight:rope",
    "item:trials:crafter",
    "item:endermanoverhaul:corrupted_shield{Damage:0}",
    "item:create:schematicannon",
    "item:create:schematic_table",
    "item:create:empty_schematic",
    "item:create:schematic_and_quill",
    "item:kubejs:ab_quest",
    "item:kubejs:dynamicl_quest",
    "item:kubejs:easiers_quest",
    "item:kubejs:cr_quest",
    "item:kubejs:dt_quest",
    "item:kubejs:endr_quest",
    "item:kubejs:pbosses_quest",
    "item:kubejs:svc_quest",
    "item:kubejs:backp_quest",
    "item:kubejs:config_quest",
    "item:kubejs:moreover_quest",
    "item:kubejs:biomesop_quest",
    "item:kubejs:bount_quest",
    "item:kubejs:healingc_quest",
    "item:kubejs:equipc_quest",
    "item:kubejs:bugs_quest",
    "item:kubejs:camera_quest",
    "item:kubejs:skinc_quest",
    "item:kubejs:shouldersr_quest",
    "item:kubejs:carryon_quest",
    "item:kubejs:chorses_quest",
    "item:kubejs:serenes_quest",
    "item:kubejs:handc_quest",
    "item:kubejs:cwand_quest",
    "item:kubejs:farmerd_quest",
    "item:kubejs:vinery_quest",
    "item:kubejs:immersiveeng_quest",
    "item:kubejs:iceandfire_quest",
    "item:kubejs:hexerei_quest",
    "item:kubejs:aquac_quest",
    "item:kubejs:immersivea_quest",
    "item:kubejs:horsee_quest",
    "item:kubejs:targetd_quest",
    "item:kubejs:spiceof_quest",
    "item:kubejs:deeperad_quest",
    "item:kubejs:create_quest",
    "item:kubejs:ageings_quest",
    "item:kubejs:brewery_quest",
    "item:kubejs:bakery_quest",
    "item:kubejs:twilight_quest",
    "item:kubejs:botania_quest",
    "item:kubejs:bossesomd_quest",
    "item:kubejs:bumblezone_quest",
    "item:kubejs:storaged_quest",
    "item:kubejs:smalls_quest",
    "item:kubejs:aether_quest",
    "item:kubejs:blues_quest",
    "item:kubejs:bloodm_quest",
    "item:kubejs:samuraid_quest",
    "item:kubejs:shielde_quest",
    "item:kubejs:scubag_quest",
    "item:kubejs:roots_quest",
    "item:kubejs:aquamirae_quest",
    "item:kubejs:alexsm_quest",
    "item:kubejs:mowzie_quest",
    "item:kubejs:paraglider_quest",
    "item:kubejs:naturec_quest",
    "item:kubejs:cataclysm_quest",
    "item:kubejs:alexsc_quest",
    "item:kubejs:clouds_quest",
    "item:ironchest:obsidian_chest",
    "item:ironchest:dirt_chest",
    "item:ironchest:trapped_obsidian_chest",
    "item:ironchest:trapped_dirt_chest",
    "item:ironchest:trapped_crystal_chest",
    "item:ironchest:crystal_chest",
    "item:ironchest:diamond_to_crystal_chest_upgrade",
    "item:ironchest:diamond_to_obsidian_chest_upgrade"
  ]
}